{"DOI": "10.1002/jgrd.50308", "URL": "http://dx.doi.org/10.1002/jgrd.50308", "publisher": "American Geophysical Union (AGU)", "authors": [{"author": "Charland A. M.", "affiliation": "Department of Meteorology and Climate Science San Jos\u00e9 State University  San Jos\u00e9 California USA, Now at Dept. of Atmospheric Sciences University of Utah  Salt Lake City Utah 84112 USA"}, {"author": "Clements C. B.", "affiliation": "Department of Meteorology and Climate Science San Jos\u00e9 State University  San Jos\u00e9 California USA"}], "title": "Kinematic structure of a wildland fire plume observed by Doppler lidar", "journal_name": "Journal of Geophysical Research: Atmospheres", "last_audited_on": "3/13/2016", "publicly_accessible_on_publisher_site": "4/29/2013", "license_type": "VOR", "licenseUrl": "http://onlinelibrary.wiley.com/termsAndConditions#vor", "grant_ids": ["https://www.nsf.gov/awardsearch/showAward?AWD_ID=0960300"], "updated": "3/10/2024", "added": "3/6/2016", "orcid_profile": [{"ORCID": "http://orcid.org/0000-0001-9999-8621", "_id": "5e3657e03541867b49f05fed", "family": "Clements", "given": "Craig", "source": "orcid", "updatedAt": "2020-02-02"}], "member_id": "", "published_print": "4/27/2013", "published_online": "4/29/2013", "reuse_license_start_date": "04/29/2013", "type": "journal-article", "archived_status": "Yes", "datasets": null, "agency_portal_url": null, "funders": ["USDA"], "funderIDs": ["10.13039/100000199"], "RORID": ["https://ror.org/01na82s61"], "auditSource": "CHORUS", "Funder Source": "Crossref"}